Abdullah_Encrypt/Abdullah_Encrypt.py
Abdullah_Encrypt/__init__.py
Abdullah_Encrypt-0.0.1.dist-info/LICENSE
Abdullah_Encrypt-0.0.1.dist-info/METADATA
Abdullah_Encrypt-0.0.1.dist-info/WHEEL
Abdullah_Encrypt-0.0.1.dist-info/top_level.txt
Abdullah_Encrypt-0.0.1.dist-info/RECORD
