Metadata-Version: 2.1
Name: Abdullah-Encrypt
Version: 0.0.1
Summary: Encode and decrypt scripts
Home-page: https://github.com/abdallah34/Abdullah-Encrypt
Author: Abdullah
Author-email: abdullah.alaa.360@gmail.com
License: UNKNOWN
Project-URL: Bug Tracker, https://github.com/abdallah34/Abdullah-Encrypt
Platform: UNKNOWN
Classifier: Programming Language :: Python :: 3
Classifier: License :: OSI Approved :: MIT License
Classifier: Operating System :: OS Independent
Requires-Python: >=3.6
